WenXinAPI/V1.py
WenXinAPI/__init__.py
WenXinAPI/typings.py
WenXinAPI/version.py
revWenXin-1.0.3.dist-info/LICENSE
revWenXin-1.0.3.dist-info/METADATA
revWenXin-1.0.3.dist-info/WHEEL
revWenXin-1.0.3.dist-info/top_level.txt
revWenXin-1.0.3.dist-info/RECORD
