Metadata-Version: 2.1
Name: revWenXin
Version: 1.0.3
Summary: WenXinAPI is a simple wrapper for the official WenXin API
Home-page: https://github.com/umbrella-leaf/WenXinAPI
Author: Zhongnuo Liu
Author-email: 2313678365@qq.com
License: Apache-2.0 license
Platform: UNKNOWN
Classifier: Development Status :: 3 - Alpha
Classifier: License :: OSI Approved :: Apache Software License
Classifier: Intended Audience :: Developers
Classifier: Intended Audience :: End Users/Desktop
Classifier: Natural Language :: English
Classifier: Topic :: Software Development :: Libraries :: Python Modules
Classifier: Programming Language :: Python :: 3 :: Only
Classifier: Programming Language :: Python :: 3.6
Classifier: Programming Language :: Python :: 3.7
Classifier: Programming Language :: Python :: 3.8
Classifier: Programming Language :: Python :: 3.9
Classifier: Programming Language :: Python :: 3.10
Classifier: Programming Language :: Python :: 3.11
License-File: LICENSE
Requires-Dist: anyio (==3.7.1)
Requires-Dist: certifi (==2023.5.7)
Requires-Dist: exceptiongroup (==1.1.2)
Requires-Dist: h11 (==0.14.0)
Requires-Dist: httpcore (==0.17.3)
Requires-Dist: httpx (==0.24.1)
Requires-Dist: idna (==3.4)
Requires-Dist: sniffio (==1.3.0)
